geneticpython/__init__.py
geneticpython/callbacks/__init__.py
geneticpython/callbacks/callback.py
geneticpython/callbacks/callback_list.py
geneticpython/callbacks/history.py
geneticpython/callbacks/progbar_logger.py
geneticpython/core/__init__.py
geneticpython/core/pareto.py
geneticpython/core/population.py
geneticpython/core/individual/__init__.py
geneticpython/core/individual/individual.py
geneticpython/core/individual/solution.py
geneticpython/core/individual/chromosome/__init__.py
geneticpython/core/individual/chromosome/chromosome.py
geneticpython/core/individual/chromosome/float_chromosome.py
geneticpython/core/individual/chromosome/int_chromosome.py
geneticpython/core/operators/__init__.py
geneticpython/core/operators/crossover/__init__.py
geneticpython/core/operators/crossover/crossover.py
geneticpython/core/operators/crossover/kruskal_crossover.py
geneticpython/core/operators/crossover/order_crossover.py
geneticpython/core/operators/crossover/point_crossover.py
geneticpython/core/operators/crossover/prim_crossover.py
geneticpython/core/operators/crossover/sbx_crossover.py
geneticpython/core/operators/crossover/uniform_crossover.py
geneticpython/core/operators/mutation/__init__.py
geneticpython/core/operators/mutation/flip_bit_mutation.py
geneticpython/core/operators/mutation/inversion_mutation.py
geneticpython/core/operators/mutation/mutation.py
geneticpython/core/operators/mutation/mutation_compact.py
geneticpython/core/operators/mutation/polynomial_mutation.py
geneticpython/core/operators/mutation/scramble_mutation.py
geneticpython/core/operators/mutation/swap_mutation.py
geneticpython/core/operators/mutation/tree_mutation.py
geneticpython/core/operators/replacement/__init__.py
geneticpython/core/operators/replacement/rank_replacement.py
geneticpython/core/operators/replacement/replacement.py
geneticpython/core/operators/replacement/roulette_wheel_replacement.py
geneticpython/core/operators/selection/__init__.py
geneticpython-0.0.3.dist-info/LICENSE
geneticpython-0.0.3.dist-info/METADATA
geneticpython-0.0.3.dist-info/WHEEL
geneticpython-0.0.3.dist-info/top_level.txt
geneticpython-0.0.3.dist-info/RECORD
