Metadata-Version: 2.1
Name: geneticpython
Version: 0.0.3
Summary: A simple and friendly Python framework for genetic-based algorithms
Author: Ngoc Bui
Author-email: ngocjr7@gmail.com
Project-URL: Bug Tracker, https://github.com/ngocjr7/geneticpython/issues
Project-URL: Documentation, https://github.com/ngocjr7/geneticpython/blob/master/README.md
Project-URL: Source Code, https://github.com/ngocjr7/geneticpython
Requires-Python: >=3.6
License-File: LICENSE
Requires-Dist: cycler (>=0.10.0)
Requires-Dist: kiwisolver (>=1.2.0)
Requires-Dist: matplotlib (>=3.3.0)
Requires-Dist: numpy (>=1.19.1)
Requires-Dist: Pillow (>=7.2.0)
Requires-Dist: pyparsing (>=2.4.7)
Requires-Dist: python-dateutil (>=2.8.1)
Requires-Dist: six (>=1.15.0)
Requires-Dist: tqdm (>=4.48.1)
